<?xml version="1.0" encoding="utf-8"?>
<rdf:RDF
  xmlns:dcterms="http://purl.org/dc/terms/"
  xmlns:skos="http://www.w3.org/2004/02/skos/core#"
  xmlns:arches="http://localhost:8000/"
  xmlns:rdf="http://www.w3.org/1999/02/22-rdf-syntax-ns#"
>
  <skos:Concept rdf:about="http://localhost:8000/83feb7c3-77fa-4b2e-be38-8fb746667d71">
    <arches:sortorder rdf:datatype="http://www.w3.org/2001/XMLSchema#integer">2</arches:sortorder>
    <dcterms:identifier>http://www.archesproject.org/83feb7c3-77fa-4b2e-be38-8fb746667d71</dcterms:identifier>
    <skos:prefLabel xml:lang="en">box</skos:prefLabel>
    <skos:inScheme>
      <skos:ConceptScheme rdf:about="http://localhost:8000/0206cda2-95a5-4667-b830-40296a34fe30">
        <dcterms:title>Container units</dcterms:title>
      </skos:ConceptScheme>
    </skos:inScheme>
  </skos:Concept>
  <skos:Concept rdf:about="http://localhost:8000/72a86b7f-c556-4394-865e-c4483d6fdfec">
    <skos:prefLabel xml:lang="en">plan chest</skos:prefLabel>
    <skos:inScheme rdf:resource="http://localhost:8000/0206cda2-95a5-4667-b830-40296a34fe30"/>
    <arches:sortorder rdf:datatype="http://www.w3.org/2001/XMLSchema#integer">7</arches:sortorder>
    <dcterms:identifier>http://www.archesproject.org/72a86b7f-c556-4394-865e-c4483d6fdfec</dcterms:identifier>
  </skos:Concept>
  <skos:Concept rdf:about="http://localhost:8000/75176355-82e0-4edd-b48f-60196865137e">
    <arches:sortorder rdf:datatype="http://www.w3.org/2001/XMLSchema#integer">3</arches:sortorder>
    <skos:prefLabel xml:lang="en">cabinet</skos:prefLabel>
    <skos:inScheme rdf:resource="http://localhost:8000/0206cda2-95a5-4667-b830-40296a34fe30"/>
    <dcterms:identifier>http://localhost:8000/75176355-82e0-4edd-b48f-60196865137e</dcterms:identifier>
  </skos:Concept>
  <skos:Concept rdf:about="http://localhost:8000/94bb9a80-1af9-47ec-9535-900cfae9dd5b">
    <dcterms:identifier>http://localhost:8000/94bb9a80-1af9-47ec-9535-900cfae9dd5b</dcterms:identifier>
    <skos:prefLabel xml:lang="en">cupboard</skos:prefLabel>
    <skos:inScheme rdf:resource="http://localhost:8000/0206cda2-95a5-4667-b830-40296a34fe30"/>
    <arches:sortorder rdf:datatype="http://www.w3.org/2001/XMLSchema#integer">4</arches:sortorder>
  </skos:Concept>
  <skos:Concept rdf:about="http://localhost:8000/9adab730-8fcc-498d-ba52-de1f97110cf9">
    <skos:prefLabel xml:lang="en">bay</skos:prefLabel>
    <skos:inScheme rdf:resource="http://localhost:8000/0206cda2-95a5-4667-b830-40296a34fe30"/>
    <arches:sortorder rdf:datatype="http://www.w3.org/2001/XMLSchema#integer">0</arches:sortorder>
    <dcterms:identifier>http://www.archesproject.org/9adab730-8fcc-498d-ba52-de1f97110cf9</dcterms:identifier>
  </skos:Concept>
  <skos:Concept rdf:about="http://localhost:8000/de4628c7-761f-4493-902a-f93163d89645">
    <dcterms:identifier>http://localhost:8000/de4628c7-761f-4493-902a-f93163d89645</dcterms:identifier>
    <arches:sortorder rdf:datatype="http://www.w3.org/2001/XMLSchema#integer">9</arches:sortorder>
    <skos:inScheme rdf:resource="http://localhost:8000/0206cda2-95a5-4667-b830-40296a34fe30"/>
    <skos:prefLabel xml:lang="en">sheet</skos:prefLabel>
  </skos:Concept>
  <skos:Concept rdf:about="http://localhost:8000/48b30d6b-6dcb-4f8c-8d09-7ae1ebc9008e">
    <skos:inScheme rdf:resource="http://localhost:8000/0206cda2-95a5-4667-b830-40296a34fe30"/>
    <skos:prefLabel xml:lang="en">bookcase</skos:prefLabel>
    <dcterms:identifier>http://localhost:8000/48b30d6b-6dcb-4f8c-8d09-7ae1ebc9008e</dcterms:identifier>
    <arches:sortorder rdf:datatype="http://www.w3.org/2001/XMLSchema#integer">1</arches:sortorder>
  </skos:Concept>
  <skos:Concept rdf:about="http://localhost:8000/34b62784-1bf3-43dc-8fae-94c4c84b4d5d">
    <dcterms:identifier>http://localhost:8000/34b62784-1bf3-43dc-8fae-94c4c84b4d5d</dcterms:identifier>
    <skos:inScheme rdf:resource="http://localhost:8000/0206cda2-95a5-4667-b830-40296a34fe30"/>
    <skos:prefLabel xml:lang="en">file/folder</skos:prefLabel>
    <arches:sortorder rdf:datatype="http://www.w3.org/2001/XMLSchema#integer">6</arches:sortorder>
  </skos:Concept>
  <skos:Concept rdf:about="http://localhost:8000/5c19e67b-d053-4900-b01c-e8d6cede66a4">
    <dcterms:identifier>http://www.archesproject.org/5c19e67b-d053-4900-b01c-e8d6cede66a4</dcterms:identifier>
    <skos:prefLabel xml:lang="en">rack</skos:prefLabel>
    <arches:sortorder rdf:datatype="http://www.w3.org/2001/XMLSchema#integer">8</arches:sortorder>
    <skos:inScheme rdf:resource="http://localhost:8000/0206cda2-95a5-4667-b830-40296a34fe30"/>
  </skos:Concept>
  <skos:Concept rdf:about="http://localhost:8000/93e0d3b5-cb0b-4d27-971e-78d926291c49">
    <arches:sortorder rdf:datatype="http://www.w3.org/2001/XMLSchema#integer">10</arches:sortorder>
    <skos:inScheme rdf:resource="http://localhost:8000/0206cda2-95a5-4667-b830-40296a34fe30"/>
    <skos:prefLabel xml:lang="en">shelf</skos:prefLabel>
    <dcterms:identifier>http://www.archesproject.org/93e0d3b5-cb0b-4d27-971e-78d926291c49</dcterms:identifier>
  </skos:Concept>
  <skos:Concept rdf:about="http://localhost:8000/5ff15b63-02ef-4bbc-aa3b-3eec02a0d2fe">
    <skos:prefLabel xml:lang="en">file</skos:prefLabel>
    <arches:sortorder rdf:datatype="http://www.w3.org/2001/XMLSchema#integer">5</arches:sortorder>
    <dcterms:identifier>http://www.archesproject.org/5ff15b63-02ef-4bbc-aa3b-3eec02a0d2fe</dcterms:identifier>
    <skos:inScheme rdf:resource="http://localhost:8000/0206cda2-95a5-4667-b830-40296a34fe30"/>
  </skos:Concept>
</rdf:RDF>
