{
    [
        {
            "attributenodes": [
                {
                    "description": "construction_phase_type",
                    "nodeid": "77e8f28d-efdc-11eb-afe4-a87eeabdefba"
                },
                {
                    "description": "primary_reference_number",
                    "nodeid": "325a2f33-efe4-11eb-b0bb-a87eeabdefba"
                },
                {
                    "description": "description",
                    "nodeid": "ba345577-b554-11ea-a9ee-f875a44e0e11"
                },
                {
                    "description": "use_phase_period",
                    "nodeid": "b2133e72-efdc-11eb-a68d-a87eeabdefba"
                },
                {
                    "description": "functional_type",
                    "nodeid": "b2133e6b-efdc-11eb-aa04-a87eeabdefba"
                },
                {
                    "description": "cultural_period",
                    "nodeid": "77e8f29d-efdc-11eb-b890-a87eeabdefba"
                },
                {
                    "description": "monument_name",
                    "nodeid": "676d47ff-9c1c-11ea-b07f-f875a44e0e11"
                },
                {
                    "description": "area_name",
                    "nodeid": "87d3c3ea-f44f-11eb-b532-a87eeabdefba"
                },
                {
                    "description": "monument_type",
                    "nodeid": "77e90834-efdc-11eb-b2b9-a87eeabdefba"
                },
                {
                    "description": "resource_id",
                    "nodeid": "325a430a-efe4-11eb-810b-a87eeabdefba"
                }
            ],
            "description": "Heritage sites",
            "geometry_node_id": "87d3872b-f44f-11eb-bd0c-a87eeabdefba",
            "ismixedgeometrytypes": false,
            "slug": "heritage_sites",
            "spatialviewid": "27318c10-adc4-421c-9e93-9c007ceee035"
        },
    ]
}